<?xml version="1.0" encoding="utf-8" ?>
<dwsync>
<file name="CBC.php" server="ftp.goservizi.it:2121/goservizi.it/html/" local="130662242326664665" remote="130701403800000000" Dst="1" />
<file name="CTR.php" server="ftp.goservizi.it:2121/goservizi.it/html/" local="130662242321564658" remote="130701403800000000" Dst="1" />
<file name="ECB.php" server="ftp.goservizi.it:2121/goservizi.it/html/" local="130662242318864654" remote="130701403800000000" Dst="1" />
<file name="CFB.php" server="ftp.goservizi.it:2121/goservizi.it/html/" local="130662242323964661" remote="130701403800000000" Dst="1" />
<file name="NCFB.php" server="ftp.goservizi.it:2121/goservizi.it/html/" local="130662242316264650" remote="130701403800000000" Dst="1" />
<file name="NOFB.php" server="ftp.goservizi.it:2121/goservizi.it/html/" local="130662242313664647" remote="130701403800000000" Dst="1" />
<file name="OFB.php" server="ftp.goservizi.it:2121/goservizi.it/html/" local="130662242307964639" remote="130701403800000000" Dst="1" />
<file name="PCBC.php" server="ftp.goservizi.it:2121/goservizi.it/html/" local="130662242305364635" remote="130701403800000000" Dst="1" />
<file name="Raw.php" server="ftp.goservizi.it:2121/goservizi.it/html/" local="130662242302764631" remote="130701403800000000" Dst="1" />
<file name="Stream.php" server="ftp.goservizi.it:2121/goservizi.it/html/" local="130662242300364628" remote="130701403800000000" Dst="1" />
</dwsync>